sudoku_helper/__init__.py
sudoku_helper/_grid.py
sudoku_helper/_types.py
sudoku_helper/solver.py
sudoku_helper/validator.py
sudoku_helper-0.1.0.dist-info/METADATA
sudoku_helper-0.1.0.dist-info/WHEEL
sudoku_helper-0.1.0.dist-info/RECORD
