Metadata-Version: 2.4
Name: sudoku-helper
Version: 0.1.0
Summary: A Python library for solving and validating Sudoku puzzles.
Author: Suez Dirie
Author-email: suez.dirie@hotmail.com
Requires-Python: >=3.10
Classifier: Programming Language :: Python :: 3
Classifier: Programming Language :: Python :: 3.10
Classifier: Programming Language :: Python :: 3.11
Classifier: Programming Language :: Python :: 3.12
Classifier: Programming Language :: Python :: 3.13
Classifier: Programming Language :: Python :: 3.14
